<?xml version="1.0" encoding="UTF-8"?>
<objects serializationModel="Studio.02.02.00">
	<object class="AudioFile" id="{b7704c9d-0e37-4dc6-a5ab-f8b2fffdfb4e}">
		<property name="assetPath">
			<value>munchies.ogg</value>
		</property>
		<property name="frequencyInKHz">
			<value>44.0999985</value>
		</property>
		<property name="channelCount">
			<value>2</value>
		</property>
		<property name="length">
			<value>0.46285714285714286</value>
		</property>
		<relationship name="masterAssetFolder">
			<destination>{d56e1613-a998-492e-b41c-8088f254bc9a}</destination>
		</relationship>
	</object>
</objects>
